py5jupyter/__init__.py
py5jupyter/_version.py
py5jupyter/kernels/__init__.py
py5jupyter/kernels/py5/__init__.py
py5jupyter/kernels/py5/__main__.py
py5jupyter/kernels/py5/install.py
py5jupyter/kernels/py5/kernel.py
py5jupyter/kernels/py5/resources/logo-32x32.png
py5jupyter/kernels/py5/resources/logo-64x64.png
py5jupyter/kernels/py5bot/__init__.py
py5jupyter/kernels/py5bot/__main__.py
py5jupyter/kernels/py5bot/install.py
py5jupyter/kernels/py5bot/kernel.py
py5jupyter/kernels/py5bot/py5bot.py
py5jupyter/kernels/py5bot/resources/logo-32x32.png
py5jupyter/kernels/py5bot/resources/logo-64x64.png
py5jupyter/tests/__init__.py
py5jupyter/tests/conftest.py
py5jupyter/tests/test_example.py
py5jupyter/tests/test_nbextension_path.py
py5jupyter/widgets/__init__.py
py5jupyter/widgets/_frontend.py
py5jupyter/widgets/sketchportal.py
py5jupyter-0.2.1a0.dist-info/METADATA
py5jupyter-0.2.1a0.dist-info/WHEEL
py5jupyter-0.2.1a0.dist-info/licenses/LICENSE
py5jupyter-0.2.1a0.dist-info/RECORD
