Metadata-Version: 2.3
Name: py5jupyter
Version: 0.2.1a0
Summary: Jupyter tools for py5
Project-URL: Bug Tracker, https://github.com/py5coding/py5jupyter/issues
Project-URL: Documentation, https://py5coding.org/
Project-URL: Download, https://pypi.org/project/py5jupyter
Project-URL: Homepage, https://py5coding.org/
Project-URL: Source Code, https://github.com/py5coding/py5jupyter
Author-email: Jim Schmitz <jim@ixora.io>
License:                   GNU LESSER GENERAL PUBLIC LICENSE
License-File: LICENSE
Keywords: IPython,Jupyter,Processing,Widgets
Classifier: Development Status :: 3 - Alpha
Classifier: Intended Audience :: Developers
Classifier: Intended Audience :: Education
Classifier: Intended Audience :: Science/Research
Classifier: License :: OSI Approved :: GNU Lesser General Public License v2 (LGPLv2)
Classifier: Programming Language :: Java
Classifier: Programming Language :: Python :: 3.9
Classifier: Programming Language :: Python :: 3.10
Classifier: Programming Language :: Python :: 3.11
Classifier: Programming Language :: Python :: 3.12
Classifier: Topic :: Artistic Software
Classifier: Topic :: Multimedia :: Graphics
Requires-Python: >=3.9
Requires-Dist: ipykernel>=6.29.5
Requires-Dist: ipython>=8.18
Requires-Dist: jupyter>=1.0
Requires-Dist: py5>=0.10.1a1
Requires-Dist: traitlets>=5.14
Provides-Extra: docs
Requires-Dist: jupyter-sphinx; extra == 'docs'
Requires-Dist: nbsphinx; extra == 'docs'
Requires-Dist: nbsphinx-link; extra == 'docs'
Requires-Dist: pypandoc; extra == 'docs'
Requires-Dist: pytest-check-links; extra == 'docs'
Requires-Dist: recommonmark; extra == 'docs'
Requires-Dist: sphinx-rtd-theme; extra == 'docs'
Requires-Dist: sphinx>=1.5; extra == 'docs'
Provides-Extra: examples
Provides-Extra: test
Requires-Dist: nbval; extra == 'test'
Requires-Dist: pytest-cov; extra == 'test'
Requires-Dist: pytest>=4.6; extra == 'test'
